{"nodes": [{"id": "testfcm_runner", "label": "testfcm-runner.mjs (E2E Testing)", "file_type": "code", "source_file": "task/TESTFCM-WORKFLOW.md", "source_location": null, "source_url": null, "captured_at": null, "author": null, "contributor": null}], "edges": [{"source": "free_coding_models_project", "target": "testfcm_runner", "relation": "orchestrated_by", "confidence": "EXTRACTED", "confidence_score": 1.0, "source_file": "task/TESTFCM-WORKFLOW.md", "source_location": null, "weight": 1.0}], "hyperedges": []}